patch_requests.py
patch_requests-0.3.1.dist-info/LICENSE.md
patch_requests-0.3.1.dist-info/METADATA
patch_requests-0.3.1.dist-info/WHEEL
patch_requests-0.3.1.dist-info/top_level.txt
patch_requests-0.3.1.dist-info/RECORD
