Metadata-Version: 2.1
Name: patch-requests
Version: 0.3.1
Summary: Simple patching of `requests` calls
Home-page: https://github.com/Raekkeri/patch-requests
Author: Teemu Husso
Author-email: teemu.husso@gmail.com
Keywords: requests,tests,mock,patch
License-File: LICENSE.md
Requires-Dist: setuptools
